SimCADO-0.7.dist-info/METADATA
SimCADO-0.7.dist-info/RECORD
SimCADO-0.7.dist-info/WHEEL
SimCADO-0.7.dist-info/top_level.txt
simcado/__init__.py
simcado/commands.py
simcado/detector.py
simcado/fv_psf.py
simcado/image_plane_utils.py
simcado/nghxrg.py
simcado/optics.py
simcado/psf.py
simcado/simulation.py
simcado/source.py
simcado/spatial.py
simcado/spectral.py
simcado/utils.py
simcado/version.py
