Metadata-Version: 2.1
Name: SimCADO
Version: 0.7
Summary: SimCADO: The MICADO Instrument simulator
Home-page: https://simcado.readthedocs.io/en/latest/
Author: Kieran Leschinski, Oliver Czoske, Miguel Verdugo
Author-email: kieran.leschinski@unive.ac.at,
License: MIT
Platform: UNKNOWN
Classifier: Programming Language :: Python :: 3
Classifier: License :: OSI Approved :: MIT License
Classifier: Operating System :: OS Independent
Classifier: Intended Audience :: Science/Research
Classifier: Topic :: Scientific/Engineering :: Astronomy
Requires-Dist: numpy (>1.10.4)
Requires-Dist: scipy (>0.17)
Requires-Dist: astropy (>1.1.2)
Requires-Dist: wget (>3.0)
Requires-Dist: requests (>2.0)
Requires-Dist: synphot (>0.1)
Requires-Dist: matplotlib (>1.5.0)
Requires-Dist: poppy (>0.4)
Requires-Dist: pyyaml
